<?xml version="1.0" encoding="UTF-8"?>
<!DOCTYPE listaventas [
    <!ELEMENT listaventas   (venta+)>
    <!ELEMENT venta          (ventaacredito|ventainmediata)>
    <!ELEMENT ventaacredito  (fechafinpago?, cantidad)>
    <!ELEMENT ventainmediata (cantidad, divisa)>
    <!ELEMENT fechafinpago   (#PCDATA)>
    <!ELEMENT cantidad       (#PCDATA)>
    <!ELEMENT divisa         (#PCDATA)>

    ]>
<listaventas>
    <venta>
        <ventaacredito>
            <fechafinpago>22-10-2021</fechafinpago>
            <cantidad>21000</cantidad>
        </ventaacredito>
    </venta>
    <venta>
        <ventainmediata>
            <cantidad>1800</cantidad>
            <divisa>euros</divisa>
        </ventainmediata>
    </venta>
    <venta>
        <ventaacredito>
            <cantidad>21000</cantidad>
        </ventaacredito>
    </venta>
</listaventas>
